Workbook

Sheet Raw_data
A1: Date | B1: Region | C1: Country | D1: City | E1: Product_Category | F1: Product_Name | G1: Customer_ID | H1: Customer_Type | I1: Sales_Channel | J1: Order_ID | K1: Quantity | L1: Unit_Price | M1: Discount_% | N1: Revenue | O1: Cost | P1: Profit | Q1: Payment_Mode | R1: Order_Status | S1: Sales_Rep | T1: Customer_Rating | W1: =5000/365 -> 13.69863
A2: 45658 | B2: East | C2: USA | D2: Bangalore | E2: Services | F2: Product C | G2: 96826 | H2: New | I2: Online | J2: 714751 | K2: 7 | L2: 4705 | M2: 15 | N2: 35461 | O2: 20748 | P2: 4896 | Q2: UPI | R2: Returned | S2: Rep B | T2: 4
A3: 45658 | B3: West | C3: USA | D3: Bangalore | E3: Services | F3: Product C | G3: 60530 | H3: Existing | I3: Partner | J3: 613036 | K3: 8 | L3: 2654 | M3: 0 | N3: 10739 | O3: 19499 | P3: 3649 | Q3: UPI | R3: Returned | S3: Rep D | T3: 1
A4: 45658 | B4: North | C4: USA | D4: London | E4: Services | F4: Product A | G4: 91099 | H4: Existing | I4: Partner | J4: 809244 | K4: 7 | L4: 2844 | M4: 10 | N4: 7976 | O4: 9416 | P4: 2531 | Q4: UPI | R4: Cancelled | S4: Rep C | T4: 5
A5: 45658 | B5: East | C5: USA | D5: Dubai | E5: Software | F5: Product C | G5: 35888 | H5: New | I5: Partner | J5: 349668 | K5: 6 | L5: 4423 | M5: 0 | N5: 35890 | O5: 1846 | P5: 16696 | Q5: UPI | R5: Cancelled | S5: Rep B | T5: 1
A6: 45658 | B6: East | C6: UK | D6: Bangalore | E6: Hardware | F6: Product C | G6: 37491 | H6: New | I6: Partner | J6: 105291 | K6: 7 | L6: 2354 | M6: 15 | N6: 6368 | O6: 24085 | P6: 18829 | Q6: Credit Card | R6: Completed | S6: Rep B | T6: 1
A7: 45658 | B7: West | C7: USA | D7: New York | E7: Software | F7: Product D | G7: 42352 | H7: Existing | I7: Partner | J7: 534409 | K7: 4 | L7: 4368 | M7: 20 | N7: 5023 | O7: 16211 | P7: 8968 | Q7: Net Banking | R7: Returned | S7: Rep B | T7: 5
A8: 45658 | B8: North | C8: India | D8: Bangalore | E8: Hardware | F8: Product C | G8: 31676 | H8: Existing | I8: Partner | J8: 738132 | K8: 1 | L8: 4290 | M8: 0 | N8: 10975 | O8: 15582 | P8: 2202 | Q8: Net Banking | R8: Cancelled | S8: Rep C | T8: 2
A9: 45658 | B9: North | C9: USA | D9: New York | E9: Software | F9: Product C | G9: 75836 | H9: New | I9: Offline | J9: 889554 | K9: 5 | L9: 3532 | M9: 0 | N9: 27785 | O9: 22819 | P9: 6507 | Q9: UPI | R9: Completed | S9: Rep D | T9: 4
A10: 45658 | B10: East | C10: UK | D10: Bangalore | E10: Hardware | F10: Product C | G10: 47463 | H10: Existing | I10: Online | J10: 629164 | K10: 8 | L10: 1344 | M10: 10 | N10: 43899 | O10: 5069 | P10: -3392 | Q10: UPI | R10: Returned | S10: Rep D | T10: 2
A11: 45658 | B11: South | C11: USA | D11: New York | E11: Software | F11: Product B | G11: 58990 | H11: Existing | I11: Partner | J11: 343082 | K11: 6 | L11: 2207 | M11: 15 | N11: 49664 | O11: 20340 | P11: -1106 | Q11: Credit Card | R11: Completed | S11: Rep C | T11: 2
A12: 45658 | B12: East | C12: India | D12: Bangalore | E12: Services | F12: Product A | G12: 96544 | H12: Existing | I12: Offline | J12: 567876 | K12: 5 | L12: 2507 | M12: 10 | N12: 11522 | O12: 21771 | P12: 1788 | Q12: Credit Card | R12: Cancelled | S12: Rep C | T12: 4
A13: 45658 | B13: East | C13: UK | D13: Bangalore | E13: Software | F13: Product D | G13: 73627 | H13: New | I13: Online | J13: 157147 | K13: 2 | L13: 1773 | M13: 20 | N13: 44721 | O13: 25031 | P13: 12480 | Q13: UPI | R13: Completed | S13: Rep D | T13: 2
A14: =A2+1 -> 45659 | B14: East | C14: UK | D14: Delhi | E14: Software | F14: Product C | G14: 30221 | H14: Existing | I14: Online | J14: 232895 | K14: 5 | L14: 4934 | M14: 5 | N14: 41428 | O14: 27837 | P14: 12010 | Q14: UPI | R14: Returned | S14: Rep D | T14: 3
A15: =A3+1 -> 45659 | B15: East | C15: India | D15: New York | E15: Services | F15: Product A | G15: 95837 | H15: Existing | I15: Online | J15: 939084 | K15: 3 | L15: 2604 | M15: 15 | N15: 16176 | O15: 7911 | P15: 12674 | Q15: Net Banking | R15: Cancelled | S15: Rep D | T15: 1
A16: =A4+1 -> 45659 | B16: West | C16: India | D16: New York | E16: Services | F16: Product C | G16: 82843 | H16: New | I16: Partner | J16: 726665 | K16: 2 | L16: 3467 | M16: 20 | N16: 23433 | O16: 10775 | P16: 16101 | Q16: Net Banking | R16: Returned | S16: Rep A | T16: 3
A17: =A5+1 -> 45659 | B17: North | C17: India | D17: New York | E17: Hardware | F17: Product B | G17: 61313 | H17: New | I17: Partner | J17: 813564 | K17: 3 | L17: 4742 | M17: 20 | N17: 20605 | O17: 24132 | P17: 14795 | Q17: Net Banking | R17: Completed | S17: Rep B | T17: 4
A18: =A6+1 -> 45659 | B18: West | C18: India | D18: Mumbai | E18: Hardware | F18: Product B | G18: 39251 | H18: Existing | I18: Partner | J18: 543598 | K18: 4 | L18: 1712 | M18: 0 | N18: 21126 | O18: 18354 | P18: -2856 | Q18: UPI | R18: Completed | S18: Rep A | T18: 5
A19: =A7+1 -> 45659 | B19: West | C19: India | D19: Bangalore | E19: Hardware | F19: Product C | G19: 56586 | H19: New | I19: Online | J19: 503603 | K19: 2 | L19: 2795 | M19: 10 | N19: 3096 | O19: 25069 | P19: -4101 | Q19: Cash | R19: Completed | S19: Rep A | T19: 5
A20: =A8+1 -> 45659 | B20: West | C20: UK | D20: New York | E20: Software | F20: Product C | G20: 84418 | H20: New | I20: Online | J20: 726987 | K20: 4 | L20: 2697 | M20: 0 | N20: 26575 | O20: 29548 | P20: 8903 | Q20: Credit Card | R20: Cancelled | S20: Rep C | T20: 4
A21: =A9+1 -> 45659 | B21: East | C21: UK | D21: London | E21: Hardware | F21: Product C | G21: 63884 | H21: Existing | I21: Offline | J21: 335427 | K21: 4 | L21: 3784 | M21: 0 | N21: 31840 | O21: 18600 | P21: -4303 | Q21: Credit Card | R21: Completed | S21: Rep B | T21: 4
A22: =A10+1 -> 45659 | B22: South | C22: USA | D22: Mumbai | E22: Software | F22: Product B | G22: 62620 | H22: New | I22: Offline | J22: 855140 | K22: 6 | L22: 2764 | M22: 5 | N22: 48743 | O22: 22490 | P22: 17464 | Q22: Credit Card | R22: Cancelled | S22: Rep B | T22: 2
A23: =A11+1 -> 45659 | B23: North | C23: USA | D23: Delhi | E23: Software | F23: Product B | G23: 20040 | H23: Existing | I23: Offline | J23: 643268 | K23: 5 | L23: 2110 | M23: 10 | N23: 20487 | O23: 27214 | P23: 6122 | Q23: UPI | R23: Completed | S23: Rep D | T23: 1
A24: =A12+1 -> 45659 | B24: South | C24: UAE | D24: New York | E24: Hardware | F24: Product A | G24: 81677 | H24: Existing | I24: Offline | J24: 517440 | K24: 7 | L24: 1918 | M24: 5 | N24: 6729 | O24: 22937 | P24: 15439 | Q24: UPI | R24: Completed | S24: Rep C | T24: 3
A25: =A13+1 -> 45659 | B25: West | C25: USA | D25: New York | E25: Hardware | F25: Product D | G25: 55878 | H25: New | I25: Online | J25: 369265 | K25: 7 | L25: 2286 | M25: 20 | N25: 17229 | O25: 27697 | P25: 2231 | Q25: Credit Card | R25: Cancelled | S25: Rep C | T25: 4
... A5001: =A4989+1 -> 46074 | B5001: West | C5001: India | D5001: Dubai | E5001: Software | F5001: Product C | G5001: 23707 | H5001: New | I5001: Offline | J5001: 392429 | K5001: 5 | L5001: 2569 | M5001: 5 | N5001: 29710 | O5001: 23896 | P5001: 2792 | Q5001: UPI | R5001: Completed | S5001: Rep B | T5001: 5

Sheet Clean_data
A1: Date | B1: Region | C1: Country | D1: City | E1: Product_Category | F1: Product_Name | G1: Customer_ID | H1: Customer_Type | I1: Sales_Channel | J1: Order_ID | K1: Quantity | L1: Unit_Price | M1: Discount_% | N1: Revenue | O1: Cost | P1: Profit | Q1: Payment_Mode | R1: Order_Status | S1: Sales_Rep | T1: Customer_Rating | U1: Column1 | V1: hi
A2: 45658 | B2: East | C2: =VLOOKUP(D2, City_Mapping!A:B, 2, FALSE) -> India | D2: Bangalore | E2: Services | F2: Product C | G2: 96826 | H2: New | I2: Online | J2: 714751 | K2: 7 | L2: 4705 | M2: =Table1[[#This Row],[Column1]]/100 -> 0.15 | N2: =Table1[[#This Row],[Unit_Price]]*Table1[[#This Row],[Quantity]]*(1-Table1[[#This Row],[Discount_%]]) -> 27994.75 | O2: 20748 | P2: =Table1[[#This Row],[Revenue]]-Table1[[#This Row],[Cost]] -> 7246.75 | Q2: UPI | R2: Returned | S2: Rep B | T2: 4 | U2: 15 | V2: =TEXT(Table1[[#This Row],[Date]],"mmm-yyyy") -> Jan-2025
A3: 45658 | B3: West | C3: =VLOOKUP(D3, City_Mapping!A:B, 2, FALSE) -> India | D3: Bangalore | E3: Services | F3: Product C | G3: 60530 | H3: Existing | I3: Partner | J3: 613036 | K3: 8 | L3: 2654 | M3: =Table1[[#This Row],[Column1]]/100 -> 0 | N3: =Table1[[#This Row],[Unit_Price]]*Table1[[#This Row],[Quantity]]*(1-Table1[[#This Row],[Discount_%]]) -> 21232 | O3: 19499 | P3: =Table1[[#This Row],[Revenue]]-Table1[[#This Row],[Cost]] -> 1733 | Q3: UPI | R3: Returned | S3: Rep D | T3: 1 | U3: 0 | V3: =TEXT(Table1[[#This Row],[Date]],"mmm-yyyy") -> Jan-2025
A4: 45658 | B4: North | C4: =VLOOKUP(D4, City_Mapping!A:B, 2, FALSE) -> UK | D4: London | E4: Services | F4: Product A | G4: 91099 | H4: Existing | I4: Partner | J4: 809244 | K4: 7 | L4: 2844 | M4: =Table1[[#This Row],[Column1]]/100 -> 0.1 | N4: =Table1[[#This Row],[Unit_Price]]*Table1[[#This Row],[Quantity]]*(1-Table1[[#This Row],[Discount_%]]) -> 17917.2 | O4: 9416 | P4: =Table1[[#This Row],[Revenue]]-Table1[[#This Row],[Cost]] -> 8501.2 | Q4: UPI | R4: Cancelled | S4: Rep C | T4: 5 | U4: 10 | V4: =TEXT(Table1[[#This Row],[Date]],"mmm-yyyy") -> Jan-2025
A5: 45658 | B5: East | C5: =VLOOKUP(D5, City_Mapping!A:B, 2, FALSE) -> UAE | D5: Dubai | E5: Software | F5: Product C | G5: 35888 | H5: New | I5: Partner | J5: 349668 | K5: 6 | L5: 4423 | M5: =Table1[[#This Row],[Column1]]/100 -> 0 | N5: =Table1[[#This Row],[Unit_Price]]*Table1[[#This Row],[Quantity]]*(1-Table1[[#This Row],[Discount_%]]) -> 26538 | O5: 1846 | P5: =Table1[[#This Row],[Revenue]]-Table1[[#This Row],[Cost]] -> 24692 | Q5: UPI | R5: Cancelled | S5: Rep B | T5: 1 | U5: 0 | V5: =TEXT(Table1[[#This Row],[Date]],"mmm-yyyy") -> Jan-2025
A6: 45658 | B6: East | C6: =VLOOKUP(D6, City_Mapping!A:B, 2, FALSE) -> India | D6: Bangalore | E6: Hardware | F6: Product C | G6: 37491 | H6: New | I6: Partner | J6: 105291 | K6: 7 | L6: 2354 | M6: =Table1[[#This Row],[Column1]]/100 -> 0.15 | N6: =Table1[[#This Row],[Unit_Price]]*Table1[[#This Row],[Quantity]]*(1-Table1[[#This Row],[Discount_%]]) -> 14006.3 | O6: 24085 | P6: =Table1[[#This Row],[Revenue]]-Table1[[#This Row],[Cost]] -> -10078.7 | Q6: Credit Card | R6: Completed | S6: Rep B | T6: 1 | U6: 15 | V6: =TEXT(Table1[[#This Row],[Date]],"mmm-yyyy") -> Jan-2025
A7: 45658 | B7: West | C7: =VLOOKUP(D7, City_Mapping!A:B, 2, FALSE) -> USA | D7: New York | E7: Software | F7: Product D | G7: 42352 | H7: Existing | I7: Partner | J7: 534409 | K7: 4 | L7: 4368 | M7: =Table1[[#This Row],[Column1]]/100 -> 0.2 | N7: =Table1[[#This Row],[Unit_Price]]*Table1[[#This Row],[Quantity]]*(1-Table1[[#This Row],[Discount_%]]) -> 13977.6 | O7: 16211 | P7: =Table1[[#This Row],[Revenue]]-Table1[[#This Row],[Cost]] -> -2233.4 | Q7: Net Banking | R7: Returned | S7: Rep B | T7: 5 | U7: 20 | V7: =TEXT(Table1[[#This Row],[Date]],"mmm-yyyy") -> Jan-2025
A8: 45658 | B8: North | C8: =VLOOKUP(D8, City_Mapping!A:B, 2, FALSE) -> India | D8: Bangalore | E8: Hardware | F8: Product C | G8: 31676 | H8: Existing | I8: Partner | J8: 738132 | K8: 1 | L8: 4290 | M8: =Table1[[#This Row],[Column1]]/100 -> 0 | N8: =Table1[[#This Row],[Unit_Price]]*Table1[[#This Row],[Quantity]]*(1-Table1[[#This Row],[Discount_%]]) -> 4290 | O8: 15582 | P8: =Table1[[#This Row],[Revenue]]-Table1[[#This Row],[Cost]] -> -11292 | Q8: Net Banking | R8: Cancelled | S8: Rep C | T8: 2 | U8: 0 | V8: =TEXT(Table1[[#This Row],[Date]],"mmm-yyyy") -> Jan-2025
A9: 45658 | B9: North | C9: =VLOOKUP(D9, City_Mapping!A:B, 2, FALSE) -> USA | D9: New York | E9: Software | F9: Product C | G9: 75836 | H9: New | I9: Offline | J9: 889554 | K9: 5 | L9: 3532 | M9: =Table1[[#This Row],[Column1]]/100 -> 0 | N9: =Table1[[#This Row],[Unit_Price]]*Table1[[#This Row],[Quantity]]*(1-Table1[[#This Row],[Discount_%]]) -> 17660 | O9: 22819 | P9: =Table1[[#This Row],[Revenue]]-Table1[[#This Row],[Cost]] -> -5159 | Q9: UPI | R9: Completed | S9: Rep D | T9: 4 | U9: 0 | V9: =TEXT(Table1[[#This Row],[Date]],"mmm-yyyy") -> Jan-2025
A10: 45658 | B10: East | C10: =VLOOKUP(D10, City_Mapping!A:B, 2, FALSE) -> India | D10: Bangalore | E10: Hardware | F10: Product C | G10: 47463 | H10: Existing | I10: Online | J10: 629164 | K10: 8 | L10: 1344 | M10: =Table1[[#This Row],[Column1]]/100 -> 0.1 | N10: =Table1[[#This Row],[Unit_Price]]*Table1[[#This Row],[Quantity]]*(1-Table1[[#This Row],[Discount_%]]) -> 9676.8 | O10: 5069 | P10: =Table1[[#This Row],[Revenue]]-Table1[[#This Row],[Cost]] -> 4607.8 | Q10: UPI | R10: Returned | S10: Rep D | T10: 2 | U10: 10 | V10: =TEXT(Table1[[#This Row],[Date]],"mmm-yyyy") -> Jan-2025
A11: 45658 | B11: South | C11: =VLOOKUP(D11, City_Mapping!A:B, 2, FALSE) -> USA | D11: New York | E11: Software | F11: Product B | G11: 58990 | H11: Existing | I11: Partner | J11: 343082 | K11: 6 | L11: 2207 | M11: =Table1[[#This Row],[Column1]]/100 -> 0.15 | N11: =Table1[[#This Row],[Unit_Price]]*Table1[[#This Row],[Quantity]]*(1-Table1[[#This Row],[Discount_%]]) -> 11255.7 | O11: 20340 | P11: =Table1[[#This Row],[Revenue]]-Table1[[#This Row],[Cost]] -> -9084.3 | Q11: Credit Card | R11: Completed | S11: Rep C | T11: 2 | U11: 15 | V11: =TEXT(Table1[[#This Row],[Date]],"mmm-yyyy") -> Jan-2025
A12: 45658 | B12: East | C12: =VLOOKUP(D12, City_Mapping!A:B, 2, FALSE) -> India | D12: Bangalore | E12: Services | F12: Product A | G12: 96544 | H12: Existing | I12: Offline | J12: 567876 | K12: 5 | L12: 2507 | M12: =Table1[[#This Row],[Column1]]/100 -> 0.1 | N12: =Table1[[#This Row],[Unit_Price]]*Table1[[#This Row],[Quantity]]*(1-Table1[[#This Row],[Discount_%]]) -> 11281.5 | O12: 21771 | P12: =Table1[[#This Row],[Revenue]]-Table1[[#This Row],[Cost]] -> -10489.5 | Q12: Credit Card | R12: Cancelled | S12: Rep C | T12: 4 | U12: 10 | V12: =TEXT(Table1[[#This Row],[Date]],"mmm-yyyy") -> Jan-2025
A13: 45658 | B13: East | C13: =VLOOKUP(D13, City_Mapping!A:B, 2, FALSE) -> India | D13: Bangalore | E13: Software | F13: Product D | G13: 73627 | H13: New | I13: Online | J13: 157147 | K13: 2 | L13: 1773 | M13: =Table1[[#This Row],[Column1]]/100 -> 0.2 | N13: =Table1[[#This Row],[Unit_Price]]*Table1[[#This Row],[Quantity]]*(1-Table1[[#This Row],[Discount_%]]) -> 2836.8 | O13: 25031 | P13: =Table1[[#This Row],[Revenue]]-Table1[[#This Row],[Cost]] -> -22194.2 | Q13: UPI | R13: Completed | S13: Rep D | T13: 2 | U13: 20 | V13: =TEXT(Table1[[#This Row],[Date]],"mmm-yyyy") -> Jan-2025
A14: =A2+1 -> 45659 | B14: East | C14: =VLOOKUP(D14, City_Mapping!A:B, 2, FALSE) -> India | D14: Delhi | E14: Software | F14: Product C | G14: 30221 | H14: Existing | I14: Online | J14: 232895 | K14: 5 | L14: 4934 | M14: =Table1[[#This Row],[Column1]]/100 -> 0.05 | N14: =Table1[[#This Row],[Unit_Price]]*Table1[[#This Row],[Quantity]]*(1-Table1[[#This Row],[Discount_%]]) -> 23436.5 | O14: 27837 | P14: =Table1[[#This Row],[Revenue]]-Table1[[#This Row],[Cost]] -> -4400.5 | Q14: UPI | R14: Returned | S14: Rep D | T14: 3 | U14: 5 | V14: =TEXT(Table1[[#This Row],[Date]],"mmm-yyyy") -> Jan-2025
A15: =A3+1 -> 45659 | B15: East | C15: =VLOOKUP(D15, City_Mapping!A:B, 2, FALSE) -> USA | D15: New York | E15: Services | F15: Product A | G15: 95837 | H15: Existing | I15: Online | J15: 939084 | K15: 3 | L15: 2604 | M15: =Table1[[#This Row],[Column1]]/100 -> 0.15 | N15: =Table1[[#This Row],[Unit_Price]]*Table1[[#This Row],[Quantity]]*(1-Table1[[#This Row],[Discount_%]]) -> 6640.2 | O15: 7911 | P15: =Table1[[#This Row],[Revenue]]-Table1[[#This Row],[Cost]] -> -1270.8 | Q15: Net Banking | R15: Cancelled | S15: Rep D | T15: 1 | U15: 15 | V15: =TEXT(Table1[[#This Row],[Date]],"mmm-yyyy") -> Jan-2025
A16: =A4+1 -> 45659 | B16: West | C16: =VLOOKUP(D16, City_Mapping!A:B, 2, FALSE) -> USA | D16: New York | E16: Services | F16: Product C | G16: 82843 | H16: New | I16: Partner | J16: 726665 | K16: 2 | L16: 3467 | M16: =Table1[[#This Row],[Column1]]/100 -> 0.2 | N16: =Table1[[#This Row],[Unit_Price]]*Table1[[#This Row],[Quantity]]*(1-Table1[[#This Row],[Discount_%]]) -> 5547.2 | O16: 10775 | P16: =Table1[[#This Row],[Revenue]]-Table1[[#This Row],[Cost]] -> -5227.8 | Q16: Net Banking | R16: Returned | S16: Rep A | T16: 3 | U16: 20 | V16: =TEXT(Table1[[#This Row],[Date]],"mmm-yyyy") -> Jan-2025
A17: =A5+1 -> 45659 | B17: North | C17: =VLOOKUP(D17, City_Mapping!A:B, 2, FALSE) -> USA | D17: New York | E17: Hardware | F17: Product B | G17: 61313 | H17: New | I17: Partner | J17: 813564 | K17: 3 | L17: 4742 | M17: =Table1[[#This Row],[Column1]]/100 -> 0.2 | N17: =Table1[[#This Row],[Unit_Price]]*Table1[[#This Row],[Quantity]]*(1-Table1[[#This Row],[Discount_%]]) -> 11380.8 | O17: 24132 | P17: =Table1[[#This Row],[Revenue]]-Table1[[#This Row],[Cost]] -> -12751.2 | Q17: Net Banking | R17: Completed | S17: Rep B | T17: 4 | U17: 20 | V17: =TEXT(Table1[[#This Row],[Date]],"mmm-yyyy") -> Jan-2025
A18: =A6+1 -> 45659 | B18: West | C18: =VLOOKUP(D18, City_Mapping!A:B, 2, FALSE) -> India | D18: Mumbai | E18: Hardware | F18: Product B | G18: 39251 | H18: Existing | I18: Partner | J18: 543598 | K18: 4 | L18: 1712 | M18: =Table1[[#This Row],[Column1]]/100 -> 0 | N18: =Table1[[#This Row],[Unit_Price]]*Table1[[#This Row],[Quantity]]*(1-Table1[[#This Row],[Discount_%]]) -> 6848 | O18: 18354 | P18: =Table1[[#This Row],[Revenue]]-Table1[[#This Row],[Cost]] -> -11506 | Q18: UPI | R18: Completed | S18: Rep A | T18: 5 | U18: 0 | V18: =TEXT(Table1[[#This Row],[Date]],"mmm-yyyy") -> Jan-2025
A19: =A7+1 -> 45659 | B19: West | C19: =VLOOKUP(D19, City_Mapping!A:B, 2, FALSE) -> India | D19: Bangalore | E19: Hardware | F19: Product C | G19: 56586 | H19: New | I19: Online | J19: 503603 | K19: 2 | L19: 2795 | M19: =Table1[[#This Row],[Column1]]/100 -> 0.1 | N19: =Table1[[#This Row],[Unit_Price]]*Table1[[#This Row],[Quantity]]*(1-Table1[[#This Row],[Discount_%]]) -> 5031 | O19: 25069 | P19: =Table1[[#This Row],[Revenue]]-Table1[[#This Row],[Cost]] -> -20038 | Q19: Cash | R19: Completed | S19: Rep A | T19: 5 | U19: 10 | V19: =TEXT(Table1[[#This Row],[Date]],"mmm-yyyy") -> Jan-2025
A20: =A8+1 -> 45659 | B20: West | C20: =VLOOKUP(D20, City_Mapping!A:B, 2, FALSE) -> USA | D20: New York | E20: Software | F20: Product C | G20: 84418 | H20: New | I20: Online | J20: 726987 | K20: 4 | L20: 2697 | M20: =Table1[[#This Row],[Column1]]/100 -> 0 | N20: =Table1[[#This Row],[Unit_Price]]*Table1[[#This Row],[Quantity]]*(1-Table1[[#This Row],[Discount_%]]) -> 10788 | O20: 29548 | P20: =Table1[[#This Row],[Revenue]]-Table1[[#This Row],[Cost]] -> -18760 | Q20: Credit Card | R20: Cancelled | S20: Rep C | T20: 4 | U20: 0 | V20: =TEXT(Table1[[#This Row],[Date]],"mmm-yyyy") -> Jan-2025
A21: =A9+1 -> 45659 | B21: East | C21: =VLOOKUP(D21, City_Mapping!A:B, 2, FALSE) -> UK | D21: London | E21: Hardware | F21: Product C | G21: 63884 | H21: Existing | I21: Offline | J21: 335427 | K21: 4 | L21: 3784 | M21: =Table1[[#This Row],[Column1]]/100 -> 0 | N21: =Table1[[#This Row],[Unit_Price]]*Table1[[#This Row],[Quantity]]*(1-Table1[[#This Row],[Discount_%]]) -> 15136 | O21: 18600 | P21: =Table1[[#This Row],[Revenue]]-Table1[[#This Row],[Cost]] -> -3464 | Q21: Credit Card | R21: Completed | S21: Rep B | T21: 4 | U21: 0 | V21: =TEXT(Table1[[#This Row],[Date]],"mmm-yyyy") -> Jan-2025
A22: =A10+1 -> 45659 | B22: South | C22: =VLOOKUP(D22, City_Mapping!A:B, 2, FALSE) -> India | D22: Mumbai | E22: Software | F22: Product B | G22: 62620 | H22: New | I22: Offline | J22: 855140 | K22: 6 | L22: 2764 | M22: =Table1[[#This Row],[Column1]]/100 -> 0.05 | N22: =Table1[[#This Row],[Unit_Price]]*Table1[[#This Row],[Quantity]]*(1-Table1[[#This Row],[Discount_%]]) -> 15754.8 | O22: 22490 | P22: =Table1[[#This Row],[Revenue]]-Table1[[#This Row],[Cost]] -> -6735.2 | Q22: Credit Card | R22: Cancelled | S22: Rep B | T22: 2 | U22: 5 | V22: =TEXT(Table1[[#This Row],[Date]],"mmm-yyyy") -> Jan-2025
A23: =A11+1 -> 45659 | B23: North | C23: =VLOOKUP(D23, City_Mapping!A:B, 2, FALSE) -> India | D23: Delhi | E23: Software | F23: Product B | G23: 20040 | H23: Existing | I23: Offline | J23: 643268 | K23: 5 | L23: 2110 | M23: =Table1[[#This Row],[Column1]]/100 -> 0.1 | N23: =Table1[[#This Row],[Unit_Price]]*Table1[[#This Row],[Quantity]]*(1-Table1[[#This Row],[Discount_%]]) -> 9495 | O23: 27214 | P23: =Table1[[#This Row],[Revenue]]-Table1[[#This Row],[Cost]] -> -17719 | Q23: UPI | R23: Completed | S23: Rep D | T23: 1 | U23: 10 | V23: =TEXT(Table1[[#This Row],[Date]],"mmm-yyyy") -> Jan-2025
A24: =A12+1 -> 45659 | B24: South | C24: =VLOOKUP(D24, City_Mapping!A:B, 2, FALSE) -> USA | D24: New York | E24: Hardware | F24: Product A | G24: 81677 | H24: Existing | I24: Offline | J24: 517440 | K24: 7 | L24: 1918 | M24: =Table1[[#This Row],[Column1]]/100 -> 0.05 | N24: =Table1[[#This Row],[Unit_Price]]*Table1[[#This Row],[Quantity]]*(1-Table1[[#This Row],[Discount_%]]) -> 12754.7 | O24: 22937 | P24: =Table1[[#This Row],[Revenue]]-Table1[[#This Row],[Cost]] -> -10182.3 | Q24: UPI | R24: Completed | S24: Rep C | T24: 3 | U24: 5 | V24: =TEXT(Table1[[#This Row],[Date]],"mmm-yyyy") -> Jan-2025
A25: =A13+1 -> 45659 | B25: West | C25: =VLOOKUP(D25, City_Mapping!A:B, 2, FALSE) -> USA | D25: New York | E25: Hardware | F25: Product D | G25: 55878 | H25: New | I25: Online | J25: 369265 | K25: 7 | L25: 2286 | M25: =Table1[[#This Row],[Column1]]/100 -> 0.2 | N25: =Table1[[#This Row],[Unit_Price]]*Table1[[#This Row],[Quantity]]*(1-Table1[[#This Row],[Discount_%]]) -> 12801.6 | O25: 27697 | P25: =Table1[[#This Row],[Revenue]]-Table1[[#This Row],[Cost]] -> -14895.4 | Q25: Credit Card | R25: Cancelled | S25: Rep C | T25: 4 | U25: 20 | V25: =TEXT(Table1[[#This Row],[Date]],"mmm-yyyy") -> Jan-2025
... A5001: =A4989+1 -> 46074 | B5001: West | C5001: =VLOOKUP(D5001, City_Mapping!A:B, 2, FALSE) -> UAE | D5001: Dubai | E5001: Software | F5001: Product C | G5001: 23707 | H5001: New | I5001: Offline | J5001: 392429 | K5001: 5 | L5001: 2569 | M5001: =Table1[[#This Row],[Column1]]/100 -> 0.05 | N5001: =Table1[[#This Row],[Unit_Price]]*Table1[[#This Row],[Quantity]]*(1-Table1[[#This Row],[Discount_%]]) -> 12202.75 | O5001: 23896 | P5001: =Table1[[#This Row],[Revenue]]-Table1[[#This Row],[Cost]] -> -11693.25 | Q5001: UPI | R5001: Completed | S5001: Rep B | T5001: 5 | U5001: 5 | V5001: =TEXT(Table1[[#This Row],[Date]],"mmm-yyyy") -> Feb-2026

Sheet City_Mapping
A1: City | B1: Correct_Country
A2: Bangalore | B2: India
A3: Mumbai | B3: India
A4: Delhi | B4: India
A5: New York | B5: USA
A6: London | B6: UK
A7: Dubai | B7: UAE

Sheet Dashboard

Sheet Pivot tables
A4: Row Labels | B4: Sum of Revenue | D4: Row Labels | E4: Sum of Profit
A5: East | B5: 15138613 | D5: East | E5: -3593338.5
A6: North | B6: 16318366 | D6: North | E6: -4111338.4
A7: South | B7: 15287875 | D7: South | E7: -3827995.6
A8: West | B8: 15432209 | D8: West | E8: -4277060.3
A9: Grand Total | B9: 62177063 | D9: Grand Total | E9: -15809733
A12: Row Labels | B12: Sum of Revenue | C12: Sum of Profit | D12: Profit Margin Rep
A13: Rep C | B13: 15872213 | C13: -3733141.5 | D13: -0.23519981
A14: Rep B | B14: 15706084 | C14: -3766211.5 | D14: -0.23979317
A15: Rep D | B15: 15804838 | C15: -3972758 | D15: -0.25136342
A16: Rep A | B16: 14793928 | C16: -4337621.8 | D16: -0.29320284
A19: Row Labels | B19: Sum of Revenue | C19: Sum of Profit | D19: Profit margin
A20: Product A | B20: 16146788 | C20: -3159133.4 | D20: -0.1956509
A21: Product C | B21: 15720350 | C21: -4355517.6 | D21: -0.27706237
A22: Product B | B22: 15400549 | C22: -4406224.2 | D22: -0.28610826
A23: Product D | B23: 14909376 | C23: -3888857.7 | D23: -0.26083302
A29: Row Labels | B29: Sum of Revenue | C29: MOM sales %
A30: Jan | B30: 9318033.6 | C30: -
A31: Feb | B31: 7131721.2 | C31: =(B31-B30)/B30 -> -0.23463238
A32: Mar | B32: 4578080.5 | C32: =(B32-B31)/B31 -> -0.35806794
A33: Apr | B33: 4589130.8 | C33: =(B33-B32)/B32 -> 0.0024137409
A34: May | B34: 4713632.1 | C34: =(B34-B33)/B33 -> 0.027129604
A35: Jun | B35: 4462852.8 | C35: =(B35-B34)/B34 -> -0.053202985
A36: Jul | B36: 4342793.7 | C36: =(B36-B35)/B35 -> -0.026901862
A37: Aug | B37: 4579107 | C37: =(B37-B36)/B36 -> 0.054415018
A38: Sep | B38: 4568519.2 | C38: =(B38-B37)/B37 -> -0.0023121867
A39: Oct | B39: 4828231.1 | C39: =(B39-B38)/B38 -> 0.056848158
A40: Nov | B40: 4442134.5 | C40: =(B40-B39)/B39 -> -0.07996646
A41: Dec | B41: 4622826.5 | C41: =(B41-B40)/B40 -> 0.04067683
A42: Grand Total | B42: 62177063

Sheet Question
A1: Build Sales, Revenue & Profit dashboards
A3: Analyze Region / Product / Sales Rep performance
A5: Find top & bottom performing products
A7: Identify loss-making orders
A9: Create KPIs & insights (MoM, trends, contribution %)
A11: Provide business recommendations
